solidkit/__init__.py
solidkit/constants.cpython-310-darwin.so
solidkit/__main__.py
solidkit/core/__init__.py
solidkit/core/decorators.cpython-310-darwin.so
solidkit/core/utils.cpython-310-darwin.so
solidkit/optimization/__init__.py
solidkit/io/ext.cpython-310-darwin.so
solidkit/io/bcs.cpython-310-darwin.so
solidkit/io/__init__.py
solidkit/io/vesta.cpython-310-darwin.so
solidkit/cli/polycrystal.cpython-310-darwin.so
solidkit/cli/dbshow.cpython-310-darwin.so
solidkit/cli/__init__.py
solidkit/cli/hardness.cpython-310-darwin.so
solidkit/cli/boundary.cpython-310-darwin.so
solidkit/cli/main.cpython-310-darwin.so
solidkit/cli/optimize.cpython-310-darwin.so
solidkit/properties/__init__.py
solidkit/properties/hardness_model.cpython-310-darwin.so
solidkit/properties/hardness.cpython-310-darwin.so
solidkit/gui/__init__.py
solidkit/gui/login.cpython-310-darwin.so
solidkit/build/polycrystal.cpython-310-darwin.so
solidkit/build/__init__.py
solidkit/build/twin.cpython-310-darwin.so
solidkit/data/elements.cpython-310-darwin.so
solidkit/data/db.cpython-310-darwin.so
solidkit/data/__init__.py
solidkit/data/files/__init__.py
solidkit/data/files/BNC.tersoff
solidkit/data/files/BCN-ms-v0.0.1.pth
solidkit-1.0.0.dev40.dist-info/RECORD
solidkit-1.0.0.dev40.dist-info/WHEEL
solidkit-1.0.0.dev40.dist-info/entry_points.txt
solidkit-1.0.0.dev40.dist-info/top_level.txt
solidkit-1.0.0.dev40.dist-info/METADATA
