Metadata-Version: 2.4
Name: solidkit
Version: 1.0.0.dev40
Summary: Solid-state Physics Simulation ToolKit
Author-email: Xuecheng Shao <shaoxc@jlu.edu.cn>
Project-URL: Homepage, https://shaoxc.com
Classifier: Intended Audience :: Science/Research
Classifier: Programming Language :: Python :: 3
Classifier: Programming Language :: Python :: 3.10
Classifier: Programming Language :: Python :: 3.11
Classifier: Programming Language :: Python :: 3.12
Classifier: Programming Language :: Python :: 3.13
Classifier: Topic :: Scientific/Engineering :: Chemistry
Classifier: Topic :: Scientific/Engineering :: Physics
Classifier: Operating System :: POSIX
Classifier: Operating System :: Unix
Classifier: Operating System :: MacOS
Requires-Python: >=3.9
Requires-Dist: numpy>=1.23.0
Requires-Dist: scipy>=1.13.0
Requires-Dist: ase>=3.26.0
Requires-Dist: typing_extensions; python_version < "3.10"
Provides-Extra: opt
Requires-Dist: mattersim>=1.2.0; extra == "opt"
Provides-Extra: extra
Requires-Dist: matscipyi>=1.1.0; extra == "extra"
Provides-Extra: test
Requires-Dist: pytest>=8.3.5; extra == "test"
Requires-Dist: pytest-cov>=6.1.1; extra == "test"
